Metadata-Version: 2.1
Name: pyCSGO
Version: 1.0
Summary: offsets csgo for python, autoupdate on, enjoy
Home-page: UNKNOWN
Author-email: adamisaev9234@gmail.com
License: UNKNOWN
Platform: UNKNOWN
